tree_sitter_ocamllex/__init__.py
tree_sitter_ocamllex/__init__.pyi
tree_sitter_ocamllex/_binding.abi3.so
tree_sitter_ocamllex/binding.c
tree_sitter_ocamllex/py.typed
tree_sitter_ocamllex/queries/highlights.scm
tree_sitter_ocamllex/queries/injections.scm
tree_sitter_ocamllex-0.24.0.dist-info/LICENSE
tree_sitter_ocamllex-0.24.0.dist-info/METADATA
tree_sitter_ocamllex-0.24.0.dist-info/WHEEL
tree_sitter_ocamllex-0.24.0.dist-info/top_level.txt
tree_sitter_ocamllex-0.24.0.dist-info/RECORD
