Metadata-Version: 2.2
Name: tree-sitter-ocamllex
Version: 0.24.0
Summary: OCamllex grammar for tree-sitter
Author: Pieter Goetschalckx
License: MIT
Project-URL: Homepage, https://github.com/314eter/tree-sitter-ocamllex
Keywords: incremental,parsing,tree-sitter,ocaml,ocamllex
Classifier: Intended Audience :: Developers
Classifier: License :: OSI Approved :: MIT License
Classifier: Topic :: Software Development :: Compilers
Classifier: Topic :: Text Processing :: Linguistic
Classifier: Typing :: Typed
Requires-Python: >=3.9
License-File: LICENSE
Provides-Extra: core
Requires-Dist: tree-sitter~=0.22; extra == "core"
